ruamel/std/pathlib/__init__.py
ruamel/std/pathlib/blake3.py
ruamel/std/pathlib/json.py
ruamel/std/pathlib/msgpack.py
ruamel/std/pathlib/tar.py
ruamel/std/pathlib/tempdir.py
ruamel.std.pathlib-0.13.0.dist-info/LICENSE
ruamel.std.pathlib-0.13.0.dist-info/METADATA
ruamel.std.pathlib-0.13.0.dist-info/WHEEL
ruamel.std.pathlib-0.13.0.dist-info/top_level.txt
ruamel.std.pathlib-0.13.0.dist-info/RECORD
