Metadata-Version: 2.1
Name: ruamel.std.pathlib
Version: 0.13.0
Summary: improvements over the standard pathlib module and pathlib2 package
Author: Anthon van der Neut
Author-email: a.van.der.neut@ruamel.eu
License: MIT License
Project-URL: Home, https://sourceforge.net/p/ruamel-std-pathlib/
Project-URL: Source, https://sourceforge.net/p/ruamel-std-pathlib/code/ci/default/tree/
Project-URL: Tracker, https://sourceforge.net/p/ruamel-std-pathlib/tickets/
Classifier: Development Status :: 4 - Beta
Classifier: Intended Audience :: Developers
Classifier: License :: OSI Approved :: MIT License
Classifier: Operating System :: OS Independent
Classifier: Programming Language :: Python
Requires-Python: >=3
License-File: LICENSE
